[{
        "name": "pedalBody",
        "color": "green",
        "size": {
            "length": 50,
            "width": 50,
            "height": 400
        },
        "placement": {
            "angle": 0,
            "axis": {
                "x": 0,
                "y": 0,
                "z": 1
            },
            "position": {
                "x": 1050,
                "y": 0,
                "z": -400
            }
        }
    },
    {
        "name": "hud",
        "color": "red",
        "size": {
            "length": 200,
            "width": 200,
            "height": 200
        },
        "placement": {
            "angle": 0,
            "axis": {
                "x": 0,
                "y": 0,
                "z": 1
            },
            "position": {
                "x": 1050,
                "y": 100,
                "z": -100
            }
        }
    },
    {
        "name": "pedalColumnFrame",
        "color": "blue",
        "size": {
            "length": 300,
            "width": 50,
            "height": 400
        },
        "placement": {
            "angle": 0,
            "axis": {
                "x": 0,
                "y": 0,
                "z": 1
            },
            "position": {
                "x": 1000,
                "y": 50,
                "z": -300
            }
        }
    },
    {
        "name": "crossCarBeam",
        "color": "yellow",
        "size": {
            "length": 1500,
            "width": 50,
            "height": 100
        },
        "placement": {
            "angle": 0,
            "axis": {
                "x": 0,
                "y": 0,
                "z": 1
            },
            "position": {
                "x": 0,
                "y": 300,
                "z": 0
            }
        }
    },
    {
        "name": "heater",
        "color": "pink",
        "size": {
            "length": 600,
            "width": 200,
            "height": 300
        },
        "placement": {
            "angle": 0,
            "axis": {
                "x": 0,
                "y": 0,
                "z": 1
            },
            "position": {
                "x": 0,
                "y": 100,
                "z": -200
            }
        }
    },
    {
        "name": "bodyStructure",
        "color": "gray",
        "size": {
            "length": 1500,
            "width": 50,
            "height": 100
        },
        "placement": {
            "angle": 0,
            "axis": {
                "x": 0,
                "y": 0,
                "z": 1
            },
            "position": {
                "x": 0,
                "y": 0,
                "z": 0
            }
        }
    },
    {
        "name": "windScreen",
        "color": "cyan",
        "size": {
            "length": 1400,
            "width": 700,
            "height": 5
        },
        "placement": {
            "angle": 45,
            "axis": {
                "x": 1,
                "y": 0,
                "z": 0
            },
            "position": {
                "x": 0,
                "y": -104.79,
                "z": 197.50
            }
        }
    },
    {
        "name": "steeringColumn",
        "color": "black",
        "cylinder": {
            "radius": 25,
            "height": 600,
            "angle": 360
        },
        "placement": {
            "angle": 65,
            "rotation": {
                "x": -1,
                "y": 0,
                "z": 0
            },
            "position": {
                "x": 1150,
                "y": 0,
                "z": -300
            }
        }
    },
    {
        "name": "steeringWheel",
        "color": "yellow",
        "cylinder": {
            "radius": 190,
            "height": 50,
            "angle": 360
        },
        "placement": {
            "angle": 65,
            "rotation": {
                "x": -1,
                "y": 0,
                "z": 0
            },
            "position": {
                "x": 1150,
                "y": 0,
                "z": -300
            }
        }
    }
]